LbSoftConfDb2Server/LbSoftConfDbObjects.py
LbSoftConfDb2Server/Neo4jEnvSetup.py
LbSoftConfDb2Server/SoftConfDB.py
LbSoftConfDb2Server/SoftConfDBAdmin.py
LbSoftConfDb2Server/SoftConfDbPermission.py
LbSoftConfDb2Server/SoftConfDbXMLRPCServer.py
LbSoftConfDb2Server/__init__.py
LbSoftConfDb2Server/test/MockLogger.py
LbSoftConfDb2Server/test/TestDbConnection.py
LbSoftConfDb2Server/test/TestLbConfDb2.py
LbSoftConfDb2Server/test/TestNeo4jEnvSetup.py
LbSoftConfDb2Server/test/__init__.py
LbSoftConfDb2Server-1.2.7.dist-info/METADATA
LbSoftConfDb2Server-1.2.7.dist-info/WHEEL
LbSoftConfDb2Server-1.2.7.dist-info/entry_points.txt
LbSoftConfDb2Server-1.2.7.dist-info/top_level.txt
LbSoftConfDb2Server-1.2.7.dist-info/zip-safe
LbSoftConfDb2Server-1.2.7.dist-info/RECORD
