Metadata-Version: 2.1
Name: LbSoftConfDb2Server
Version: 1.2.7
Summary: LHCb Software configuration database 2 server
Home-page: https://gitlab.cern.ch/lhcb-core/LbSoftConfDb2Server
Author: CERN - LHCb Core Software
Author-email: lhcb-core-soft@cern.ch
License: GPLv3+
Platform: UNKNOWN
Classifier: Development Status :: 4 - Beta
Classifier: Intended Audience :: Developers
Classifier: Topic :: Software Development :: Build Tools
Classifier: License :: OSI Approved :: GNU General Public License v3 or later (GPLv3+)
Classifier: Programming Language :: Python :: 2
Classifier: Programming Language :: Python :: 2.7
Classifier: Programming Language :: Python :: 3
Classifier: Programming Language :: Python :: 3.5
Classifier: Programming Language :: Python :: 3.6
Requires-Python: >=2.7
Requires-Dist: py2neo (>=4.1.0)
Requires-Dist: LbCommon
Requires-Dist: LbEnv
Requires-Dist: LbSoftConfDb2Clients
